django_broker-0.0.6.dist-info/DESCRIPTION.rst
django_broker-0.0.6.dist-info/METADATA
django_broker-0.0.6.dist-info/metadata.json
django_broker-0.0.6.dist-info/RECORD
django_broker-0.0.6.dist-info/top_level.txt
django_broker-0.0.6.dist-info/WHEEL
exchange/__init__.py
exchange/exceptions.py
exchange/models.py
exchange/tests.py
